aiorubino/__init__.py
aiorubino/api/__init__.py
aiorubino/api/api.py
aiorubino/client/__init__.py
aiorubino/client/client.py
aiorubino/methods/__init__.py
aiorubino/methods/posts/__init__.py
aiorubino/methods/posts/posts.py
aiorubino/methods/users/__init__.py
aiorubino/methods/users/follow.py
aiorubino/methods/users/get_my_profile_info.py
aiorubino/methods/users/get_profile_highlights.py
aiorubino/methods/users/get_recent_following_posts.py
aiorubino/methods/users/unfollow.py
aiorubino/types/__init__.py
aiorubino/types/results/__init__.py
aiorubino/types/results/results.py
aiorubino-2.2.dist-info/LICENSE
aiorubino-2.2.dist-info/METADATA
aiorubino-2.2.dist-info/WHEEL
aiorubino-2.2.dist-info/top_level.txt
aiorubino-2.2.dist-info/RECORD
