Metadata-Version: 2.1
Name: aiorubino
Version: 2.2
Summary: aiorubino is asynchronous Rubino API library in Python 
Home-page: https://github.com/irvanyamirali/aiorubino
Author: AmirAli Irvany
Author-email: irvanyamirali@gmail.com
Classifier: Programming Language :: Python :: 3
Classifier: License :: OSI Approved :: MIT License
Requires-Python: >=3.6
License-File: LICENSE
Requires-Dist: aiohttp
